threecx/__init__.py
threecx/api.py
threecx/client.py
threecx/config.py
threecx/exceptions.py
threecx-0.1.1.dist-info/METADATA
threecx-0.1.1.dist-info/WHEEL
threecx-0.1.1.dist-info/licenses/LICENSE
threecx-0.1.1.dist-info/RECORD
