Metadata-Version: 2.1
Name: threecx
Version: 0.1.1
Summary: Python client for 3CX HTTP APIs with Alkivi config integration
Project-URL: Homepage, https://github.com/alkivi-sas/python-3cx
Project-URL: Issues, https://github.com/alkivi-sas/python-3cx/issues
Author: Alkivi
License: LGPL-3.0-or-later
License-File: LICENSE
Keywords: 3cx,api,client,cti,voip
Classifier: Intended Audience :: Developers
Classifier: License :: OSI Approved :: GNU Lesser General Public License v3 (LGPLv3)
Classifier: Operating System :: OS Independent
Classifier: Programming Language :: Python :: 3
Classifier: Programming Language :: Python :: 3 :: Only
Classifier: Topic :: Software Development :: Libraries :: Python Modules
Requires-Python: >=3.9
Requires-Dist: python-alkivi-config-manager>=0.1.0
Requires-Dist: requests>=2.31.0
Provides-Extra: test
Requires-Dist: pytest>=7.0; extra == 'test'
